[
  {
    "name": "Kokiri Sword",
    "type": "toggle",
    "img": "images/sword1.png",
    "codes": "OOT_SWORD_KOKIRI"
  },
  {
    "name": "Master Sword",
    "type": "toggle",
    "img": "images/sword2.png",
    "codes": "OOT_SWORD_MASTER"
  },
  {
    "name": "Biggoron Sword",
    "type": "toggle",
    "img": "images/sword3.png",
    "codes": "OOT_SWORD_GORON"
  },
  {
    "name": "Kokiri Shield",
    "type": "toggle",
    "img": "images/shield1.png",
    "codes": "OOT_SHIELD_DEKU"
  },
  {
    "name": "Hylian Shield",
    "type": "progressive",
    "allow_disabled": false,
    "stages": [
      {
        "img": "images/shield2.png",
        "img_mods": "@disabled"
      },
      {
        "img": "images/shield2.png",
        "codes": "OOT_SHIELD_HYLIAN"
      }
    ]
  },
  {
    "name": "Mirror Shield",
    "type": "progressive",
    "allow_disabled": false,
    "stages": [
      {
        "img": "images/shield3.png",
        "img_mods": "@disabled"
      },
      {
        "img": "images/shield3.png",
        "codes": "OOT_SHIELD_MIRROR,OOT_SHARED_SHIELD_MIRROR"
      }
    ]
  },
  {
    "name": "Kokiri Tunic",
    "type": "static",
    "img": "images/greentunic.png",
    "codes": "greentunic"
  },
  {
    "name": "Goron Tunic",
    "type": "toggle",
    "img": "images/redtunic.png",
    "codes": "OOT_TUNIC_GORON"
  },
  {
    "name": "Zora Tunic",
    "type": "toggle",
    "img": "images/bluetunic.png",
    "codes": "OOT_TUNIC_ZORA"
  },
  {
    "name": "Goron and Zora Tunics",
    "type": "composite_toggle",
    "codes": "tunics",
    "item_left": "redtunic",
    "item_right": "bluetunic",
    "images": [
      {
        "left": false,
        "right": false,
        "img": "images/tunics.png",
        "img_mods": "@disabled"
      },
      {
        "left": true,
        "right": false,
        "img": "images/redtunic.png"
      },
      {
        "left": false,
        "right": true,
        "img": "images/bluetunic.png"
      },
      {
        "left": true,
        "right": true,
        "img": "images/tunics.png"
      }
    ]
  },
  {
    "name": "Kokiri Boots",
    "type": "static",
    "img": "images/kokiriboots.png",
    "codes": "kokiriboots"
  },
  {
    "name": "Gerudo Membership Card",
    "type": "toggle",
    "img": "images/gerudocard.png",
    "codes": "OOT_GERUDO_CARD"
  },
  {
    "name": "Iron Boots",
    "type": "toggle",
    "img": "images/ironboots.png",
    "codes": "OOT_BOOTS_IRON"
  },
  {
    "name": "Hover Boots",
    "type": "toggle",
    "img": "images/hoverboots.png",
    "codes": "OOT_BOOTS_HOVER"
  },
  {
    "name": "Iron and Hover Boots",
    "type": "composite_toggle",
    "codes": "boots",
    "item_left": "ironboots",
    "item_right": "hoverboots",
    "images": [
      {
        "left": false,
        "right": false,
        "img": "images/boots.png",
        "img_mods": "@disabled"
      },
      {
        "left": true,
        "right": false,
        "img": "images/ironboots.png"
      },
      {
        "left": false,
        "right": true,
        "img": "images/hoverboots.png"
      },
      {
        "left": true,
        "right": true,
        "img": "images/boots.png"
      }
    ]
  },
  {
    "name": "Zora Scales",
    "type": "progressive",
    "stages": [
      {
        "img": "images/scale1.png",
        "codes": "OOT_SCALE"
      },
      {
        "img": "images/scale2.png",
        "codes": "OOT_GOLDSCALE"
      }
    ]
  },
  {
    "name": "Strength Upgrades",
    "type": "progressive",
    "stages": [
      {
        "img": "images/lift1.png",
        "codes": "OOT_STRENGTH"
      },
      {
        "img": "images/lift2.png",
        "codes": "OOT_STRENGTH2"
      },
      {
        "img": "images/lift3.png",
        "codes": "OOT_STRENGTH3"
      }
    ]
  }
]